{
    "Maharashtra": {
        "description": {
            "para1": "Curious about how successful startups register in record time? Our exclusive video reveals the proven steps to secure your Private Limited Company registration hassle-free. ",
            "para2": "Skip the legal confusion and fast-track your business dreams—no hidden tricks!",
            "para3": "Click the 'Talk to Experts' button or call us at +91 8447748163 to get started."
        },
        "content": {
            "navigationBar": [
                {
                    "href": "#what-is-private-limited-company",
                    "title": "What is Private Limited Company?"
                },
                {
                    "href": "#eligibility-criteria",
                    "title": "Eligibility Criteria"
                },
                {
                    "href": "#benefits-of-private-company-registration",
                    "title": "Benefits"
                },
                {
                    "href": "#categories",
                    "title": "Key Features"
                },
                {
                    "href": "#documents-required-for-registration",
                    "title": "Documents Required"
                },
                {
                    "href": "#step-by-step-procedure",
                    "title": "Step-by-Step Procedure"
                },
                {
                    "href": "#cost-and-penalties",
                    "title": "Cost and Penalties"
                },
                {
                    "href": "#why-choose-register-karo",
                    "title": "Why Choose RegisterKaro"
                },
                {
                    "href": "#company-registration-authorisation",
                    "title": "Company Registration Authorization"
                },
                {
                    "href": "#challenges-and-solutions",
                    "title": "Challenges & Solutions"
                }
            ],
            "para1": "A Private Limited Company is a modern and robust business structure that provides limited liability and a distinct legal identity. In Maharashtra, this formation is a preferred choice for both startups and established enterprises, as it streamlines legal processes while protecting the owners' personal assets. With private limited company registration in india, businesses can enjoy enhanced credibility and a structured framework that supports sustainable growth.",
            "para2": "At RegisterKaro, we assist you with every step—from understanding the private limited company registration fees india to compiling the necessary documents—ensuring full compliance with regulatory norms. Our expert team provides detailed guidance, simplifying the private limited company registration process and eliminating any administrative hassles, so you can focus on building your enterprise.",
            "para3": "Begin your journey to a successful Private Limited Company in Maharashtra with RegisterKaro. We are committed to offering professional advice and efficient services that address every detail, including private limited company registration fees india and the complete set of registration documents. Let us simplify your business formation today!",
            "eligibilityCriteria": {
                "para1": "Anyone, including Indian citizens and foreign nationals, can register a Private Limited Company in Manipur if they meet the necessary legal requirements.",
                "para2": "To register your Private Limited Company in Maharashtra, ensure the following criteria are met:",
                "eligibilityContainerArray": [
                    {
                        "icons": "UsersThree",
                        "title": "Minimum 2 Shareholders & 2 Directors"
                    },
                    {
                        "icons": "File",
                        "title": "Registered Office Address"
                    },
                    {
                        "icons": "Pen",
                        "title": "DSC & DIN"
                    },
                    {
                        "icons": "HouseLine",
                        "title": "Legal Documents"
                    },
                    {
                        "icons": "SuitcaseSimple",
                        "title": "Indian Resident Director"
                    }
                ]
            },
            "benefits": {
                "para1": "Here are some key reasons why registering your Private Limited Company in Maharashtra is a great choice:",
                "para2": "<h3>1. Limited Liability:</h3> A private limited company ensures that shareholders have limited liability. This means their personal assets are safeguarded against any debts or losses incurred by the business. Shareholders are only responsible for the company’s liabilities up to the amount they have invested, providing a critical safety net for individuals.",
                "para3": "<h3>2. Funds & Investments:</h3> Private limited companies are an attractive option for raising funds. Their structured nature and credibility make it easier to attract equity investment from venture capitalists, angel investors, and other funding sources. This structure supports growth and expansion while keeping personal financial risk to a minimum.",
                "para4": "<h3>3. Perpetual Succession:</h3> Unlike sole proprietorships or partnerships, a private limited company enjoys perpetual succession. This means the company continues to exist regardless of changes in ownership, such as the death or resignation of directors or shareholders. The continuity ensures long-term stability and reliability.",
                "para5": "<h3>4. Credibility and Trustworthiness:</h3> Being registered under the Companies Act and governed by regulatory bodies adds credibility to a private limited company. Prospective clients, investors, and partners can verify its details through official government platforms, creating a sense of trust. Transparency in company records enhances its reputation in the business world.",
                "para6": "<h3>5. Government Incentives:</h3> Registering your business as a Private Limited Company not only offers a robust legal structure but also unlocks a range of government incentives. These benefits can include tax breaks, subsidies, and other financial support schemes designed to boost growth, innovation, and market expansion. With a well-documented private limited company registration, companies are better positioned to access these government-backed initiatives, ensuring a smoother transition from startup to established enterprise.",
                "para7": "<h3>6. Evolving Business Ecosystem:</h3> Private Limited Company registration offers a structured and flexible framework that empowers businesses to adapt to an evolving business ecosystem. By registering as a Pvt Ltd company, businesses benefit from a distinct legal identity and limited liability, which not only protect personal assets but also build credibility with investors and partners in a dynamic market.",
                "benefitsArrayData": [
                    {
                        "heading": "Limited Liability",
                        "description": "Protects shareholders with limited liability, safeguarding their personal assets from business debts or losses. Shareholders are only liable up to their investment amount, offering crucial protection."
                    },
                    {
                        "heading": "Funds & Investments",
                        "description": "Appealing for raising funds due to their structured nature and credibility, attracting equity investment from venture capitalists and angel investors. This setup fosters growth while minimizing personal financial risk."
                    },
                    {
                        "heading": "Perpetual Succession",
                        "description": "The company continues to exist regardless of changes in ownership, such as the death or resignation of directors or shareholders. The continuity ensures long-term stability and reliability."
                    },
                    {
                        "heading": "Credibility and Trustworthiness",
                        "description": "Being registered under the Companies Act and regulated by official bodies boosts a private limited company's credibility. Clients, investors, and partners can verify details through government platforms."
                    },
                    {
                        "heading": "Government Incentives",
                        "description": "The Maharashtra government actively promotes startups and businesses with subsidies, tax benefits, and initiatives under programs like StartUp Maharashtra and the South West Industrial Development Scheme (NEIDS)."
                    },
                    {
                        "heading": "Evolving Business Ecosystem",
                        "description": "Maharashtra’s growing focus on innovation, incubation centers, and local entrepreneurial initiatives makes it an attractive destination for innovative businesses and startups."
                    }
                ]
            },
            "categories": {
                "para": "Private Limited Company Registration in Maharashtra is part of a wider spectrum of business formation and legal compliance services. The primary categories include:",
                "CategoriesArrayData": [
                    {
                        "categoryTitle": "Standard Private Limited Companies",
                        "categorySubtitle": " The most common registration option for SMEs includes a solid legal framework with at least two directors and up to 200 shareholders. It offers strong compliance and limited liability, making it a popular choice for entrepreneurs."
                    },
                    {
                        "categoryTitle": "Startup Focused Companies",
                        "categorySubtitle": "These registrations support innovative ventures with access to government incentives and funding, helping startups accelerate growth and market entry in Maharashtra."
                    },
                    {
                        "categoryTitle": "NRI Private Limited Companies",
                        "categorySubtitle": "Designed for non-resident Indians, this category simplifies cross-border ownership while ensuring compliance with local regulations, providing a secure structure for investment management and operational control."
                    },
                    {
                        "categoryTitle": "Sector-Specific Registrations",
                        "categorySubtitle": "This category provides tailored compliance solutions for specialized industries like IT, manufacturing, pharmaceuticals, and retail, addressing specific challenges while supporting sustainable growth."
                    },
                    {
                        "categoryTitle": "Family-Owned Business Registrations",
                        "categorySubtitle": "This category suits family-run businesses seeking to formalize operations and boost credibility, with simplified governance and clear succession planning for effective management."
                    },
                    {
                        "categoryTitle": "Expansion & Multi-location Ventures",
                        "categorySubtitle": "This registration option aids companies planning to scale in multiple regions by simplifying expansion and management. It helps businesses capitalize on local opportunities while preserving a unified corporate identity in Maharashtra."
                    }
                ],
                "columns": [
                    {
                        "label": "Category",
                        "key": "categoryTitle"
                    },
                    {
                        "label": "Description",
                        "key": "categorySubtitle"
                    }
                    
                ]
            },
            "documents_required": {
                "para": "Here is the list of documents required to register a private limited company in Maharashtra:",
                "documentsArrayData": [
                    {
                        "name": "For Directors and Shareholders",
                        "description": [
                            "PAN Card",
                            "Proof of Identity",
                            "Address Proof",
                            "Passport (for Foreign Nationals)"
                        ]
                    },
                    {
                        "name": "For the Registered Office",
                        "description": [
                            "Proof of Address",
                            "Utility Bill"
                        ]
                    },
                    {
                        "name": "For Company Registration",
                        "description": [
                            "Digital Signature Certificate",
                            "Director Identification Number",
                            "Memorandum of Association",
                            "Articles of Association"
                        ]
                    }
                ]
            },
            "stepsToRegister": {
                "para": "The process of registering a Private Limited Company in Maharashtra involves a series of steps to ensure compliance with legal and regulatory requirements. Here’s a step-by-step guide:",
                "para1": "<h2>Step 1: Obtain DSC</h2> To initiate the company registration process, you must first obtain a <a href='https://www.registerkaro.in/digital-signature-certificate' style='text-decoration:none;'>Digital Signature Certificate (DSC)</a>. A DSC (Usually Class 3 DSC) is mandatory for all subscribers and witnesses signing the Memorandum of Association (MOA) and Articles of Association (AOA).",
                "para2": "<h2>Step 2: Apply For DIN</h2> A Director Identification Number (DIN) is essential for anyone intending to serve as a company director. One DIN suffices to act as a director in multiple companies. DIN is applied through the SPICe+ (INC-32) form during the registration process.",
                "para3": "<h2>Step 3: Unique Company Name</h2> A company’s name plays a crucial role in catching attention and making the firm stand out amidst hundreds of competitors. Select a unique name and check its availability on the Company Name Search tool.",
                "para4": "<h2>Step 4: MoA & AoA</h2> The Memorandum of Association (MOA) and Articles of Association (AOA) outline the company’s objectives, internal rules, and regulations. These documents must be prepared electronically (e-MoA and e-AoA) and filed as linked forms with SPICe+. Both MOA and AOA must be digitally signed by all subscribers before submission.",
                "para5": "<h2>Step 5: SPICe+ Form</h2> Complete the SPICe+ (INC-32) form and submit it, along with the Memorandum of Association (MoA) and Articles of Association (AoA), through the MCA portal. Ensure that you attach the necessary documents, including Digital Signature Certificate (DSC), Director Identification Number (DIN), and proof of address and identity for each director.",
                "para6": "<h2>Step 6: PAN & TAN</h2> Once incorporated, apply for a Permanent Account Number (PAN) and a Tax Deduction and Collection Account Number (TAN) for tax compliance. Then, register for <a href='https://www.registerkaro.in/gst-registration' style='text-decoration:none;'>GST registration</a> if the company's turnover exceeds ₹20 lakh (₹40 lakh for certain businesses).",
                "para7": "<h2>Step 7: Compliance Filings</h2> After incorporation comes the task of getting your business legally compliant. Submit annual financial statements (AOC-4), annual returns (MGT-7), and statutory compliance reports to the ROC each year. Failure to comply can lead to penalties and legal action.",
                "para8": "<h2>Step 8: Legal Operations</h2> Now that you are set, your company (now registered as a private limited) is all set to grow. Fill your basic details on the form to get instant assistance to register your company now!   ",
                "steps": [
                    "Obtain Digital Signature Certificates (DSC)",
                    "Apply for Director Identification Number",
                    " Reserve a Unique Company Name",
                    "Draft MoA and AoA",
                    "SPICe+ Form",
                    "Apply for PAN and TAN",
                    "Compliance Filings",
                    "Successful SetUp"
                ]
            },
            "cost_penalties": {
                "para": "The cost structure for Pvt Ltd company registration in Maharashtra is variable and depends on factors such as professional service fees, statutory charges, and the complexity of your business profile. There are no fixed amounts, as expenses are tailored to each company's specific requirements and the scope of the services provided.",
                "para1": "In addition to registration fees, companies must be aware of penalties for non-compliance. In Maharashtra, failing to adhere to prescribed regulatory requirements—such as timely submission of documents or correct completion of mandatory forms—can result in fines and other legal repercussions. Ensuring meticulous preparation and strict compliance with all guidelines helps avoid these penalties and sets a solid foundation for your business growth.",
                "para2": "The total registration cost typically includes government fees, professional charges, stamp duty, and other miscellaneous expenses. These fees can vary based on factors such as the authorized share capital and the complexity of the business structure. ",
                "para3": "In addition to the registration expenses, it’s important to be aware of potential penalties associated with non-compliance. Delays, inaccuracies in documentation, or failure to adhere to statutory requirements may result in fines or legal repercussions."
            },
            "whyChooseRegisterKaro": {
                "para1": "At RegisterKaro, we simplify the entire process of company registration with our expert services.",
                "features": [
                    "Trusted by 50,000+ Clients",
                    "Proven track record of 10,000+ successful registrations per month.",
                    "Fast document preparation and filing process.",
                    "Assistance at every step from consultation to compliance.",
                    "Transparent and budget-friendly pricing."
                ],
                "image": ""
            },
            "companyRegistrationAuthorization": {
                "para1": "Obtaining company registration authorization in Maharashtra is a critical step in ensuring your business complies with all legal and regulatory standards. This authorization confirms that your private limited company has been vetted and approved by the appropriate state and national authorities, providing you with a clear, legally recognized status. With this formal validation, businesses gain enhanced credibility and the assurance that their operations adhere to the highest standards of compliance.",
                "para2": "Take decisive action by partnering with experienced professionals who specialize in corporate compliance. Our expert team streamlines the documentation and filing process, ensuring that every regulatory requirement is met with precision."
            },
            "challenges_solutions": {
                "para": "Registering a company in Maharashtra presents its own set of challenges. Complex documentation, evolving statutory mandates, and occasional delays in the approval process can create significant hurdles for new businesses. Errors in filings or misinterpretations of legal requirements can lead to setbacks that affect both timelines and budgets.",
                "para1": "To navigate these issues, seek expert guidance for thorough documentation reviews and proactive communication with regulatory authorities. By adopting a solution-oriented approach, you can expedite the process and ensure compliance, turning challenges into opportunities for a smooth registration experience."
            }
        }
    },
    "Madhya Pradesh": {
        "description": {
            "para1": "Curious about how successful startups register in record time? Our exclusive video reveals the proven steps to secure your Private Limited Company registration hassle-free. ",
            "para2": "Skip the legal confusion and fast-track your business dreams—no hidden tricks!",
            "para3": "Click the 'Talk to Experts' button or call us at +91 8447748163 to get started."
        },
        "content": {
            "navigationBar": [
                {
                    "href": "#what-is-private-limited-company",
                    "title": "What is Private Limited Company?"
                },
                {
                    "href": "#eligibility-criteria",
                    "title": "Eligibility Criteria"
                },
                {
                    "href": "#benefits-of-private-company-registration",
                    "title": "Benefits"
                },
                {
                    "href": "#categories",
                    "title": "Key Features"
                },
                {
                    "href": "#documents-required-for-registration",
                    "title": "Documents Required"
                },
                {
                    "href": "#step-by-step-procedure",
                    "title": "Step-by-Step Procedure"
                },
                {
                    "href": "#cost-and-penalties",
                    "title": "Cost and Penalties"
                },
                {
                    "href": "#why-choose-register-karo",
                    "title": "Why Choose RegisterKaro"
                },
                {
                    "href": "#company-registration-authorisation",
                    "title": "Company Registration Authorization"
                },
                {
                    "href": "#challenges-and-solutions",
                    "title": "Challenges & Solutions"
                }
            ],
            "para1": "Private Limited Company registration in Madhya Pradesh offers businesses a structured and legally recognized entity with limited liability protection, credibility, and scalability. It is the most preferred business structure for startups and growing companies due to its ability to raise funds, separate legal identity, and ease of ownership transfer. The registration process is governed by the Companies Act, 2013, under the Ministry of Corporate Affairs (MCA), ensuring transparency and compliance.",
            "para2": "The process involves name approval, obtaining a Digital Signature Certificate (DSC) and Director Identification Number (DIN), filing incorporation documents, and registering with the Registrar of Companies (ROC), Madhya Pradesh. Additionally, businesses must draft a Memorandum of Association (MOA) and Articles of Association (AOA), defining their objectives and internal governance. Once registered, the company receives a Certificate of Incorporation (COI) along with a Company Identification Number (CIN).",
            "para3": "Begin your journey to a successful Private Limited Company in Madhya Pradesh with RegisterKaro. We are committed to offering professional advice and efficient services that address every detail, including private limited company registration fees india and the complete set of registration documents. Let us simplify your business formation today!",
            "eligibilityCriteria": {
                "para1": "Anyone, including Indian citizens and foreign nationals including entrepreneurs, startups, manufacturers, traders etc., can register a Private Limited Company in Madhya Pradesh if they meet the necessary legal requirements.",
                "para2": "To register your Private Limited Company in Madhya Pradesh, ensure the following criteria are met:",
                "eligibilityContainerArray": [
                    {
                        "icons": "UsersThree",
                        "title": "Minimum 2 Shareholders & 2 Directors"
                    },
                    {
                        "icons": "File",
                        "title": "Registered Office Address"
                    },
                    {
                        "icons": "Pen",
                        "title": "DSC & DIN"
                    },
                    {
                        "icons": "HouseLine",
                        "title": "Legal Documents"
                    },
                    {
                        "icons": "SuitcaseSimple",
                        "title": "Indian Resident Director"
                    }
                ]
            },
            "benefits": {
                "para1": "Here are some key reasons why registering your Private Limited Company in Maharashtra is a great choice:",
                "para2": "<h3>1. Limited Liability:</h3> One of the biggest advantages of registering a Private Limited Company is that the personal assets of shareholders remain protected. In case of financial losses or business debts, shareholders are only liable for the amount they invested in the company. This ensures financial security and reduces personal risk for business owners.",
                "para3": "<h3>2. Funds & Investments:</h3> Unlike sole proprietorships or partnerships, a Private Limited Company can raise capital through equity investment, venture capital, angel investors, and bank loans. Investors prefer this structure as it provides clear governance and profit-sharing mechanisms, making it easier to secure funding for business growth.",
                "para4": "<h3>3. Perpetual Succession:</h3> The existence of a Private Limited Company is not affected by the death, resignation, or departure of any shareholder or director. The company continues to operate indefinitely until legally dissolved, ensuring long-term stability and business expansion opportunities.",
                "para5": "<h3>4. Credibility and Business Growth:</h3> A Private Limited Company enjoys higher credibility and trust among customers, vendors, and investors. Being registered under the Ministry of Corporate Affairs (MCA) and following regulatory compliance boosts its reputation, which helps in securing business contracts, gaining customers, and attracting potential investors.",
                "para6": "<h3>5. Tax Benefits & Government Incentives:</h3> Businesses registered in Madhya Pradesh can avail several tax exemptions, subsidies, and government incentives, especially if registered under Startup India or the MSME (Micro, Small & Medium Enterprises) schemes. Companies also benefit from lower corporate tax rates as compared to other business structures.",
                "para7": "<h3>6. Industrial & Infrastructure Support:</h3> Madhya Pradesh provides <a href= <a href='https://www.registerkaro.in/post/guide-on-sez-in-gst' style='text-decoration:none;'>Special Economic Zones</a> Special Economic Zones (SEZs), industrial parks, and financial assistance for businesses setting up in the state. Additionally, the state offers investment subsidies, reduced electricity tariffs, and land allotments for new industries, making it an attractive destination for businesses across sectors.",
                "benefitsArrayData": [
                    {
                        "heading": "Limited Liability",
                        "description": "Protects shareholders with limited liability, safeguarding their personal assets from business debts or losses. Shareholders are only liable up to their investment amount, offering crucial protection."
                    },
                    {
                        "heading": "Funds & Investments",
                        "description": "Appealing for raising funds due to their structured nature and credibility, attracting equity investment from venture capitalists and angel investors. This setup fosters growth while minimizing personal financial risk."
                    },
                    {
                        "heading": "Perpetual Succession",
                        "description": "The company continues to exist regardless of changes in ownership, such as the death or resignation of directors or shareholders. The continuity ensures long-term stability and reliability."
                    },
                    {
                        "heading": "Credibility and Trustworthiness",
                        "description": "Being registered under the Companies Act and regulated by official bodies boosts a private limited company's credibility. Clients, investors, and partners can verify details through government platforms."
                    },
                    {
                        "heading": "Government Incentives",
                        "description": "The Madhya Pradesh government actively promotes startups and businesses with subsidies, tax benefits, and initiatives under programs like StartUp Maharashtra and the South West Industrial Development Scheme (NEIDS)."
                    },
                    {
                        "heading": "Industrial & Infrastructure Support",
                        "description": "MP offers SEZs, industrial parks, and financial support for businesses & provides investment subsidies, lower electricity tariffs, and land allotments."
                    }
                ]
            },
            "categories": {
                "para": "Private Limited Company Registration in Madhya Pradesh is part of a wider spectrum of business formation and legal compliance services. The primary categories include:",
                "CategoriesArrayData": [
                    {
                        "categoryTitle": "Standard Private Limited Companies",
                        "categorySubtitle": " The most common registration option for SMEs includes a solid legal framework with at least two directors and up to 200 shareholders. It offers strong compliance and limited liability, making it a popular choice for entrepreneurs."
                    },
                    {
                        "categoryTitle": "Startup Focused Companies",
                        "categorySubtitle": "These registrations support innovative ventures with access to government incentives and funding, helping startups accelerate growth and market entry in Madhya Pradesh."
                    },
                    {
                        "categoryTitle": "NRI Private Limited Companies",
                        "categorySubtitle": "Designed for non-resident Indians, this category simplifies cross-border ownership while ensuring compliance with local regulations, providing a secure structure for investment management and operational control."
                    },
                    {
                        "categoryTitle": "Sector-Specific Registrations",
                        "categorySubtitle": "This category provides tailored compliance solutions for specialized industries like IT, manufacturing, pharmaceuticals, and retail, addressing specific challenges while supporting sustainable growth."
                    },
                    {
                        "categoryTitle": "Family-Owned Business Registrations",
                        "categorySubtitle": "This category suits family-run businesses seeking to formalize operations and boost credibility, with simplified governance and clear succession planning for effective management."
                    },
                    {
                        "categoryTitle": "Expansion & Multi-location Ventures",
                        "categorySubtitle": "This registration option aids companies planning to scale in multiple regions by simplifying expansion and management. It helps businesses capitalize on local opportunities while preserving a unified corporate identity in Maharashtra."
                    }
                ],
                "columns": [
                    {
                        "label": "Category",
                        "key": "categoryTitle"
                    },
                    {
                        "label": "Description",
                        "key": "categorySubtitle"
                    }
                    
                ]
            },
            "documents_required": {
                "para": "Here is the list of documents required to register a private limited company in Maharashtra:",
                "documentsArrayData": [
                    {
                        "name": "For Directors and Shareholders",
                        "description": [
                            "Proof of Identity (Aadhaar Card/Voter ID/PAN Card)",
                            "Address Proof (Aadhaar Card/Voter ID)",
                            "Passport (for Foreign Nationals)"
                        ]
                    },
                    {
                        "name": "For the Registered Office",
                        "description": [
                            "Address Proof (2 Month Old Bank Statement)",
                            "Utility Bill"
                        ]
                    },
                    {
                        "name": "For Company Registration",
                        "description": [
                            "Digital Signature Certificate",
                            "Director Identification Number",
                            "Memorandum of Association ",
                            "Articles of Association "
                        ]
                    }
                ]
            },
            "stepsToRegister": {
                "para": "The process of registering a Private Limited Company in Maharashtra involves a series of steps to ensure compliance with legal and regulatory requirements. Here’s a step-by-step guide:",
                "para1": "<h2>Step 1: Obtain DSC</h2> All directors must get a <a href='https://www.registerkaro.in/digital-signature-certificate' style='text-decoration:none;'>Digital Signature Certificate (DSC)</a> from a government-approved agency. DSC is required for online document submissions on the Ministry of Corporate Affairs (MCA) portal. A DSC (Usually Class 3 DSC) is mandatory for all subscribers and witnesses signing the Memorandum of Association (MOA) and Articles of Association (AOA).",
                "para2": "<h2>Step 2: Apply For DIN</h2> Each director needs a Director Identification Number (DIN) to be recognized under the Companies Act, 2013. DIN is applied through the SPICe+ (INC-32) form during the registration process.",
                "para3": "<h2>Step 3: Unique Company Name</h2> Select a unique name and check its availability on the MCA portal using the RUN (Reserve Unique Name) service. The name should not be identical to any existing registered company or trademark.",
                "para4": "<h2>Step 4: MoA & AoA</h2> Draft the Memorandum of Association (MoA) and Articles of Association (AoA), defining the company’s objectives and operational framework. Ensure these documents align with Companies Act, 2013 regulations.",
                "para5": "<h2>Step 5: SPICe+ Form</h2> Submit the SPICe+ (INC-32) form along with MoA and AoA on the MCA portal. Attach the required documents, such as DSC, DIN, address proof, and identity proof of directors.",
                "para6": "<h2>Step 6: PAN & TAN</h2> Once incorporated, apply for a Permanent Account Number (PAN) and Tax Deduction & Collection Account Number (TAN) for tax compliance. If applicable, register for GST if the company’s turnover exceeds ₹20 lakh (₹40 lakh for specific businesses).",
                "para7": "<h2>Step 7: Compliance Filings</h2> File annual financial statements (AOC-4), annual returns (MGT-7), and statutory compliance reports with the ROC every year. Non-compliance results in penalties and legal actions.",
                "para8": "<h2>Step 8: Legal Operations</h2> Now that you are set, your company (now registered as a <a href='https://www.registerkaro.in/private-limited-company-registration' style='text-decoration:none;'>Private Limited Company </a>) is all set to grow. Fill your basic details on the form to get instant assistance to register your company now!   ",
                "steps": [
                    "Obtain Digital Signature Certificates (DSC)",
                    "Apply for Director Identification Number",
                    " Reserve a Unique Company Name",
                    "Draft MoA and AoA",
                    "SPICe+ Form",
                    "Apply for PAN and TAN",
                    "Compliance Filings",
                    "Successful SetUp"
                ]
            },
            "cost_penalties": {
                "para": "Our transparent pricing ensures that the private limited company registration fees in India and associated registration charges are competitive, making our private limited company registration process one of the most cost‑effective in Madhya Pradesh.",
                "para1": "Our competitive private limited company registration fees in India are designed to offer excellent value without any hidden charges.",
                "para2": "To avoid penalties, businesses must register with MCA and ROC before starting operations and obtain necessary tax registrations like PAN, TAN, and GST for compliance. Regular filing of annual returns, financial statements, and tax reports ensures transparency and prevents fines. ",
                "para3": "Adhering to ROC guidelines, employment laws, and industry-specific regulations minimizes legal risks. Keeping track of statutory deadlines and maintaining proper financial records helps avoid government scrutiny. Seeking professional assistance ensures smooth compliance and uninterrupted business operations."
            },
            "whyChooseRegisterKaro": {
                "para1": "At RegisterKaro, we simplify the entire process of company registration with our expert services.",
                "features": [
                    "Trusted by 50,000+ Clients",
                    "Proven track record of successful registrations across India.",
                    "Fast document preparation and filing process.",
                    "Assistance at every step from consultation to compliance.",
                    "Transparent and budget-friendly pricing."
                ],
                "image": ""
            },
            "companyRegistrationAuthorization": {
                "para1": "Obtaining company registration authorization in Maharashtra is a critical step in ensuring your business complies with all legal and regulatory standards. This authorization confirms that your private limited company has been vetted and approved by the appropriate state and national authorities, providing you with a clear, legally recognized status. With this formal validation, businesses gain enhanced credibility and the assurance that their operations adhere to the highest standards of compliance.",
                "para2": "Take decisive action by partnering with experienced professionals who specialize in corporate compliance. Our expert team streamlines the documentation and filing process, ensuring that every regulatory requirement is met with precision."
            },
            "challenges_solutions": {
                "para": "Registering a company in Maharashtra presents its own set of challenges. Complex documentation, evolving statutory mandates, and occasional delays in the approval process can create significant hurdles for new businesses. Errors in filings or misinterpretations of legal requirements can lead to setbacks that affect both timelines and budgets.",
                "para1": "To navigate these issues, seek expert guidance for thorough documentation reviews and proactive communication with regulatory authorities. By adopting a solution-oriented approach, you can expedite the process and ensure compliance, turning challenges into opportunities for a smooth registration experience."
            }
        }
    },
    "Karnataka": {
        "description": {
            "para1": "Curious about how successful startups register in record time? Our exclusive video reveals the proven steps to secure your Private Limited Company registration hassle-free. ",
            "para2": "Skip the legal confusion and fast-track your business dreams—no hidden tricks!",
            "para3": "Click the 'Talk to Experts' button or call us at +91 8447748163 to get started."
        },
        "content": {
            "navigationBar": [
                {
                    "href": "#what-is-private-limited-company",
                    "title": "What is Private Limited Company?"
                },
                {
                    "href": "#eligibility-criteria",
                    "title": "Eligibility Criteria"
                },
                {
                    "href": "#benefits-of-private-company-registration",
                    "title": "Benefits"
                },
                {
                    "href": "#categories",
                    "title": "Key Features"
                },
                {
                    "href": "#documents-required-for-registration",
                    "title": "Documents Required"
                },
                {
                    "href": "#step-by-step-procedure",
                    "title": "Step-by-Step Procedure"
                },
                {
                    "href": "#cost-and-penalties",
                    "title": "Cost and Penalties"
                },
                {
                    "href": "#why-choose-register-karo",
                    "title": "Why Choose RegisterKaro"
                },
                {
                    "href": "#company-registration-authorisation",
                    "title": "Company Registration Authorization"
                },
                {
                    "href": "#challenges-and-solutions",
                    "title": "Challenges & Solutions"
                }
            ],
            "para1": "Starting a business in Karnataka can be an exciting venture, and one of the most popular structures for entrepreneurs is the Private Limited Company Registration in Karnataka. This business model not only provides limited liability protection but also offers enhanced credibility, funding potential, and an established legal framework. By choosing Private Limited Company Registration in Karnataka, you set the stage for growth with a structure that is highly recognized in the realm of private limited company registration in India.",
            "para2": "Using a trusted platform like <a href='https://www.registerkaro.in/' style='text-decoration:none;'>RegisterKaro</a> can simplify the private limited company registration process and ensure that every step from name selection to final compliance is handled professionally. Whether you are an individual, a group of entrepreneurs, or a corporate entity looking to expand, Private Limited Company Registration in Karnataka is an ideal choice.",
            "para3": "Begin your journey to a successful Private Limited Company in Karnataka with RegisterKaro. We are committed to offering professional advice and efficient services that address every detail, including private limited company registration fees india and the complete set of registration documents. Let us simplify your business formation today!",
            "eligibilityCriteria": {
                "para1": "Anyone, including Indian citizens and foreign nationals, can register a Private Limited Company in Karnataka if they meet the necessary legal requirements.",
                "para2": "To register your Private Limited Company in Karnataka, ensure the following criteria are met:",
                "eligibilityContainerArray": [
                    {
                        "icons": "UsersThree",
                        "title": "Minimum 2 Shareholders & 2 Directors"
                    },
                    {
                        "icons": "File",
                        "title": "Registered Office Address"
                    },
                    {
                        "icons": "Pen",
                        "title": "DSC & DIN"
                    },
                    {
                        "icons": "HouseLine",
                        "title": "Legal Documents"
                    },
                    {
                        "icons": "SuitcaseSimple",
                        "title": "Indian Resident Director"
                    }
                ]
            },
            "benefits": {
                "para1": "Here are some key reasons why registering your Private Limited Company in Karnataka is a great choice:",
                "para2": "<h3>1. Limited Liability:</h3> A private limited company ensures that shareholders have limited liability. This means their personal assets are safeguarded against any debts or losses incurred by the business. Shareholders are only responsible for the company’s liabilities up to the amount they have invested, providing a critical safety net for individuals.",
                "para3": "<h3>2. Funds & Investments:</h3> Private limited companies are an attractive option for raising funds. Their structured nature and credibility make it easier to attract equity investment from venture capitalists, angel investors, and other funding sources. This structure supports growth and expansion while keeping personal financial risk to a minimum.",
                "para4": "<h3>3. Perpetual Succession:</h3> Unlike sole proprietorships or partnerships, a private limited company enjoys perpetual succession. This means the company continues to exist regardless of changes in ownership, such as the death or resignation of directors or shareholders. The continuity ensures long-term stability and reliability.",
                "para5": "<h3>4. Credibility and Trustworthiness:</h3> Being registered under the Companies Act and governed by regulatory bodies adds credibility to a private limited company. Prospective clients, investors, and partners can verify its details through official government platforms, creating a sense of trust. Transparency in company records enhances its reputation in the business world.",
                "para6": "<h3>5. Government Incentives:</h3> Registering your business as a Private Limited Company not only offers a robust legal structure but also unlocks a range of government incentives. These benefits can include tax breaks, subsidies, and other financial support schemes designed to boost growth, innovation, and market expansion. With a well-documented private limited company registration, companies are better positioned to access these government-backed initiatives, ensuring a smoother transition from startup to established enterprise.",
                "para7": "<h3>6. Evolving Business Ecosystem:</h3> Private Limited Company registration offers a structured and flexible framework that empowers businesses to adapt to an evolving business ecosystem. By registering as a Pvt Ltd company, businesses benefit from a distinct legal identity and limited liability, which not only protect personal assets but also build credibility with investors and partners in a dynamic market.",
                "benefitsArrayData": [
                    {
                        "heading": "Limited Liability",
                        "description": "Protects shareholders with limited liability, safeguarding their personal assets from business debts or losses. Shareholders are only liable up to their investment amount, offering crucial protection."
                    },
                    {
                        "heading": "Funds & Investments",
                        "description": "Appealing for raising funds due to their structured nature and credibility, attracting equity investment from venture capitalists and angel investors. This setup fosters growth while minimizing personal financial risk."
                    },
                    {
                        "heading": "Perpetual Succession",
                        "description": "The company continues to exist regardless of changes in ownership, such as the death or resignation of directors or shareholders. The continuity ensures long-term stability and reliability."
                    },
                    {
                        "heading": "Credibility and Trustworthiness",
                        "description": "A registered company gains trust among customers, suppliers, and investors, aligning with standards seen in private limited company registration in india."
                    },
                    {
                        "heading": "Tax & Government Incentives",
                        "description": "Allows companies to enjoy tax benefits and deductions along with government fund assistance not typically available to sole proprietorships or partnerships firms."
                    },
                    {
                        "heading": "Evolving Business Ecosystem",
                        "description": "Maharashtra’s growing focus on innovation, incubation centers, and local entrepreneurial initiatives makes it an attractive destination for innovative businesses and startups."
                    }
                ]
            },
            "categories": {
                "para": "Private Limited Company Registration in Karnataka is part of a wider spectrum of business formation and legal compliance services. The primary categories include:",
                "CategoriesArrayData": [
                    {
                        "categoryTitle": "Standard Private Limited Companies",
                        "categorySubtitle": " The most common registration option for SMEs includes a solid legal framework with at least two directors and up to 200 shareholders. It offers strong compliance and limited liability, making it a popular choice for entrepreneurs."
                    },
                    {
                        "categoryTitle": "Startup Focused Companies",
                        "categorySubtitle": "These registrations support innovative ventures with access to government incentives and funding, helping startups accelerate growth and market entry in Maharashtra."
                    },
                    {
                        "categoryTitle": "NRI Private Limited Companies",
                        "categorySubtitle": "Designed for non-resident Indians, this category simplifies cross-border ownership while ensuring compliance with local regulations, providing a secure structure for investment management and operational control."
                    },
                    {
                        "categoryTitle": "Sector-Specific Registrations",
                        "categorySubtitle": "This category provides tailored compliance solutions for specialized industries like IT, manufacturing, pharmaceuticals, and retail, addressing specific challenges while supporting sustainable growth."
                    },
                    {
                        "categoryTitle": "Family-Owned Business Registrations",
                        "categorySubtitle": "This category suits family-run businesses seeking to formalize operations and boost credibility, with simplified governance and clear succession planning for effective management."
                    },
                    {
                        "categoryTitle": "Expansion & Multi-location Ventures",
                        "categorySubtitle": "This registration option aids companies planning to scale in multiple regions by simplifying expansion and management. It helps businesses capitalize on local opportunities while preserving a unified corporate identity in Maharashtra."
                    }
                ],
                "columns": [
                    {
                        "label": "Category",
                        "key": "categoryTitle"
                    },
                    {
                        "label": "Description",
                        "key": "categorySubtitle"
                    }
                    
                ]
            },
            "documents_required": {
                "para": "Here is the list of documents required to register a private limited company in Karnataka:",
                "documentsArrayData": [
                    {
                        "name": "For Directors and Shareholders",
                        "description": [
                            "PAN Card",
                            "Proof of Identity",
                            "Address Proof",
                            "Passport (for Foreign Nationals)"
                        ]
                    },
                    {
                        "name": "For the Registered Office",
                        "description": [
                            "Proof of Address",
                            "Utility Bill"
                        ]
                    },
                    {
                        "name": "For Company Registration",
                        "description": [
                            "Digital Signature Certificate",
                            "Director Identification Number",
                            "Memorandum of Association",
                            "Articles of Association"
                        ]
                    }
                ]
            },
            "stepsToRegister": {
                "para": "The process of registering a Private Limited Company in Karnataka involves a series of steps to ensure compliance with legal and regulatory requirements. Here’s a step-by-step guide:",
                "para1": "<h2>Step 1: Obtain DSC</h2> To initiate the company registration process, you must first obtain a <a href='https://www.registerkaro.in/digital-signature-certificate' style='text-decoration:none;'>Digital Signature Certificate (DSC)</a>. A DSC (Usually Class 3 DSC) is mandatory for all subscribers and witnesses signing the Memorandum of Association (MOA) and Articles of Association (AOA).",
                "para2": "<h2>Step 2: Apply For DIN</h2> A Director Identification Number (DIN) is essential for anyone intending to serve as a company director. One DIN suffices to act as a director in multiple companies. DIN is applied through the SPICe+ (INC-32) form during the registration process.",
                "para3": "<h2>Step 3: Unique Company Name</h2> A company’s name plays a crucial role in catching attention and making the firm stand out amidst hundreds of competitors. Select a unique name and check its availability on the Company Name Search tool.",
                "para4": "<h2>Step 4: MoA & AoA</h2> The Memorandum of Association (MOA) and Articles of Association (AOA) outline the company’s objectives, internal rules, and regulations. These documents must be prepared electronically (e-MoA and e-AoA) and filed as linked forms with SPICe+. Both MOA and AOA must be digitally signed by all subscribers before submission.",
                "para5": "<h2>Step 5: SPICe+ Form</h2> Complete the SPICe+ (INC-32) form and submit it, along with the Memorandum of Association (MoA) and Articles of Association (AoA), through the MCA portal. Ensure that you attach the necessary documents, including Digital Signature Certificate (DSC), Director Identification Number (DIN), and proof of address and identity for each director.",
                "para6": "<h2>Step 6: PAN & TAN</h2> Once incorporated, apply for a Permanent Account Number (PAN) and a Tax Deduction and Collection Account Number (TAN) for tax compliance. Then, register for <a href='https://www.registerkaro.in/gst-registration' style='text-decoration:none;'>GST registration</a> if the company's turnover exceeds ₹20 lakh (₹40 lakh for certain businesses).",
                "para7": "<h2>Step 7: Compliance Filings</h2> After incorporation comes the task of getting your business legally compliant. Submit annual financial statements (AOC-4), annual returns (MGT-7), and statutory compliance reports to the ROC each year. Failure to comply can lead to penalties and legal action.",
                "para8": "<h2>Step 8: Legal Operations</h2> Now that you are set, your company (now registered as a private limited) is all set to grow. Fill your basic details on the form to get instant assistance to register your company now!   ",
                "steps": [
                    "Obtain Digital Signature Certificates (DSC)",
                    "Apply for Director Identification Number",
                    " Reserve a Unique Company Name",
                    "Draft MoA and AoA",
                    "SPICe+ Form",
                    "Apply for PAN and TAN",
                    "Compliance Filings",
                    "Successful SetUp"
                ]
            },
            "cost_penalties": {
                "para": "Operating a business without completing the required registration can expose entrepreneurs to significant financial and legal risks. Key points include: Monetary Fines and Financial Implications (starting from ₹1,00,000-₹5,00,000), Legal and Criminal Penalties (fine & imprisonment for up to 6 months or both), Loss of Business Credibility and Operational Restrictions, Compliance and Rectification Costs, and more.",
                "para1": "As per the guidelines set by the Ministry of Corporate Affairs (MCA) and supported by various legal sources, unregistered companies may incur fines that can range from several thousand rupees to significantly higher amounts, depending on the duration and nature of non-compliance. In certain cases, fines are levied on a per day basis for continued non-compliance.",
                "para2": "Beyond monetary fines, running a business without proper registration may attract legal actions. Section 2(68) of the Companies Act defines Private Limited Company as one that is duly registered with MCA and adheres to compliance rules. Non-registration prevents a company from getting recognized as a legal entity, and it cannot conduct business dealings effectively. ",
                "para3": "In addition to the registration expenses, it’s important to be aware of potential penalties associated with non-compliance. Delays, inaccuracies in documentation, or failure to adhere to statutory requirements may result in fines or legal repercussions."
            },
            "whyChooseRegisterKaro": {
                "para1": "At RegisterKaro, we simplify the entire process of company registration with our expert services.",
                "features": [
                    "Trusted by 50,000+ Clients",
                    "Proven track record of 10,000+ successful registrations per month.",
                    "Fast document preparation and filing process.",
                    "Assistance at every step from consultation to compliance.",
                    "Transparent and budget-friendly pricing."
                ],
                "image": ""
            },
            "companyRegistrationAuthorization": {
                "para1": "Obtaining company registration authorization in Maharashtra is a critical step in ensuring your business complies with all legal and regulatory standards. This authorization confirms that your private limited company has been vetted and approved by the appropriate state and national authorities, providing you with a clear, legally recognized status. With this formal validation, businesses gain enhanced credibility and the assurance that their operations adhere to the highest standards of compliance.",
                "para2": "Take decisive action by partnering with experienced professionals who specialize in corporate compliance. Our expert team streamlines the documentation and filing process, ensuring that every regulatory requirement is met with precision."
            },
            "challenges_solutions": {
                "para": "Registering a company in Maharashtra presents its own set of challenges. Complex documentation, evolving statutory mandates, and occasional delays in the approval process can create significant hurdles for new businesses. Errors in filings or misinterpretations of legal requirements can lead to setbacks that affect both timelines and budgets.",
                "para1": "To navigate these issues, seek expert guidance for thorough documentation reviews and proactive communication with regulatory authorities. By adopting a solution-oriented approach, you can expedite the process and ensure compliance, turning challenges into opportunities for a smooth registration experience."
            }
        }
    },
    "Gujarat": {
        "description": {
            "para1": "Curious about how successful startups register in record time? Our exclusive video reveals the proven steps to secure your Private Limited Company registration hassle-free. ",
            "para2": "Skip the legal confusion and fast-track your business dreams—no hidden tricks!",
            "para3": "Click the 'Talk to Experts' button or call us at +91 8447748163 to get started."
        },
        "content": {
            "navigationBar": [
                {
                    "href": "#what-is-private-limited-company",
                    "title": "What is Private Limited Company?"
                },
                {
                    "href": "#eligibility-criteria",
                    "title": "Eligibility Criteria"
                },
                {
                    "href": "#benefits-of-private-company-registration",
                    "title": "Benefits"
                },
                {
                    "href": "#categories",
                    "title": "Key Features"
                },
                {
                    "href": "#documents-required-for-registration",
                    "title": "Documents Required"
                },
                {
                    "href": "#step-by-step-procedure",
                    "title": "Step-by-Step Procedure"
                },
                {
                    "href": "#cost-and-penalties",
                    "title": "Cost and Penalties"
                },
                {
                    "href": "#why-choose-register-karo",
                    "title": "Why Choose RegisterKaro"
                },
                {
                    "href": "#company-registration-authorisation",
                    "title": "Company Registration Authorization"
                },
                {
                    "href": "#challenges-and-solutions",
                    "title": "Challenges & Solutions"
                }
            ],
            "para1": "Starting a business in Karnataka can be an exciting venture, and one of the most popular structures for entrepreneurs is the Private Limited Company Registration in Karnataka. This business model not only provides limited liability protection but also offers enhanced credibility, funding potential, and an established legal framework. By choosing Private Limited Company Registration in Karnataka, you set the stage for growth with a structure that is highly recognized in the realm of private limited company registration in India.",
            "para2": "Using a trusted platform like <a href='https://www.registerkaro.in/' style='text-decoration:none;'>RegisterKaro</a> can simplify the private limited company registration process and ensure that every step from name selection to final compliance is handled professionally. Whether you are an individual, a group of entrepreneurs, or a corporate entity looking to expand, Private Limited Company Registration in Karnataka is an ideal choice.",
            "para3": "Begin your journey to a successful Private Limited Company in Karnataka with RegisterKaro. We are committed to offering professional advice and efficient services that address every detail, including private limited company registration fees india and the complete set of registration documents. Let us simplify your business formation today!",
            "eligibilityCriteria": {
                "para1": "Anyone, including Indian citizens and foreign nationals, can register a Private Limited Company in Karnataka if they meet the necessary legal requirements.",
                "para2": "To register your Private Limited Company in Karnataka, ensure the following criteria are met:",
                "eligibilityContainerArray": [
                    {
                        "icons": "UsersThree",
                        "title": "Minimum 2 Shareholders & 2 Directors"
                    },
                    {
                        "icons": "File",
                        "title": "Registered Office Address"
                    },
                    {
                        "icons": "Pen",
                        "title": "DSC & DIN"
                    },
                    {
                        "icons": "HouseLine",
                        "title": "Legal Documents"
                    },
                    {
                        "icons": "SuitcaseSimple",
                        "title": "Indian Resident Director"
                    }
                ]
            },
            "benefits": {
                "para1": "Here are some key reasons why registering your Private Limited Company in Karnataka is a great choice:",
                "para2": "<h3>1. Limited Liability:</h3> A private limited company ensures that shareholders have limited liability. This means their personal assets are safeguarded against any debts or losses incurred by the business. Shareholders are only responsible for the company’s liabilities up to the amount they have invested, providing a critical safety net for individuals.",
                "para3": "<h3>2. Funds & Investments:</h3> Private limited companies are an attractive option for raising funds. Their structured nature and credibility make it easier to attract equity investment from venture capitalists, angel investors, and other funding sources. This structure supports growth and expansion while keeping personal financial risk to a minimum.",
                "para4": "<h3>3. Perpetual Succession:</h3> Unlike sole proprietorships or partnerships, a private limited company enjoys perpetual succession. This means the company continues to exist regardless of changes in ownership, such as the death or resignation of directors or shareholders. The continuity ensures long-term stability and reliability.",
                "para5": "<h3>4. Credibility and Trustworthiness:</h3> Being registered under the Companies Act and governed by regulatory bodies adds credibility to a private limited company. Prospective clients, investors, and partners can verify its details through official government platforms, creating a sense of trust. Transparency in company records enhances its reputation in the business world.",
                "para6": "<h3>5. Government Incentives:</h3> Registering your business as a Private Limited Company not only offers a robust legal structure but also unlocks a range of government incentives. These benefits can include tax breaks, subsidies, and other financial support schemes designed to boost growth, innovation, and market expansion. With a well-documented private limited company registration, companies are better positioned to access these government-backed initiatives, ensuring a smoother transition from startup to established enterprise.",
                "para7": "<h3>6. Evolving Business Ecosystem:</h3> Private Limited Company registration offers a structured and flexible framework that empowers businesses to adapt to an evolving business ecosystem. By registering as a Pvt Ltd company, businesses benefit from a distinct legal identity and limited liability, which not only protect personal assets but also build credibility with investors and partners in a dynamic market.",
                "benefitsArrayData": [
                    {
                        "heading": "Limited Liability",
                        "description": "Protects shareholders with limited liability, safeguarding their personal assets from business debts or losses. Shareholders are only liable up to their investment amount, offering crucial protection."
                    },
                    {
                        "heading": "Funds & Investments",
                        "description": "Appealing for raising funds due to their structured nature and credibility, attracting equity investment from venture capitalists and angel investors. This setup fosters growth while minimizing personal financial risk."
                    },
                    {
                        "heading": "Perpetual Succession",
                        "description": "The company continues to exist regardless of changes in ownership, such as the death or resignation of directors or shareholders. The continuity ensures long-term stability and reliability."
                    },
                    {
                        "heading": "Credibility and Trustworthiness",
                        "description": "A registered company gains trust among customers, suppliers, and investors, aligning with standards seen in private limited company registration in india."
                    },
                    {
                        "heading": "Tax & Government Incentives",
                        "description": "Allows companies to enjoy tax benefits and deductions along with government fund assistance not typically available to sole proprietorships or partnerships firms."
                    },
                    {
                        "heading": "Evolving Business Ecosystem",
                        "description": "Maharashtra’s growing focus on innovation, incubation centers, and local entrepreneurial initiatives makes it an attractive destination for innovative businesses and startups."
                    }
                ]
            },
            "categories": {
                "para": "Private Limited Company Registration in Karnataka is part of a wider spectrum of business formation and legal compliance services. The primary categories include:",
                "CategoriesArrayData": [
                    {
                        "categoryTitle": "Standard Private Limited Companies",
                        "categorySubtitle": " The most common registration option for SMEs includes a solid legal framework with at least two directors and up to 200 shareholders. It offers strong compliance and limited liability, making it a popular choice for entrepreneurs."
                    },
                    {
                        "categoryTitle": "Startup Focused Companies",
                        "categorySubtitle": "These registrations support innovative ventures with access to government incentives and funding, helping startups accelerate growth and market entry in Maharashtra."
                    },
                    {
                        "categoryTitle": "NRI Private Limited Companies",
                        "categorySubtitle": "Designed for non-resident Indians, this category simplifies cross-border ownership while ensuring compliance with local regulations, providing a secure structure for investment management and operational control."
                    },
                    {
                        "categoryTitle": "Sector-Specific Registrations",
                        "categorySubtitle": "This category provides tailored compliance solutions for specialized industries like IT, manufacturing, pharmaceuticals, and retail, addressing specific challenges while supporting sustainable growth."
                    },
                    {
                        "categoryTitle": "Family-Owned Business Registrations",
                        "categorySubtitle": "This category suits family-run businesses seeking to formalize operations and boost credibility, with simplified governance and clear succession planning for effective management."
                    },
                    {
                        "categoryTitle": "Expansion & Multi-location Ventures",
                        "categorySubtitle": "This registration option aids companies planning to scale in multiple regions by simplifying expansion and management. It helps businesses capitalize on local opportunities while preserving a unified corporate identity in Maharashtra."
                    }
                ],
                "columns": [
                    {
                        "label": "Category",
                        "key": "categoryTitle"
                    },
                    {
                        "label": "Description",
                        "key": "categorySubtitle"
                    }
                    
                ]
            },
            "documents_required": {
                "para": "Here is the list of documents required to register a private limited company in Karnataka:",
                "documentsArrayData": [
                    {
                        "name": "For Directors and Shareholders",
                        "description": [
                            "PAN Card",
                            "Proof of Identity",
                            "Address Proof",
                            "Passport (for Foreign Nationals)"
                        ]
                    },
                    {
                        "name": "For the Registered Office",
                        "description": [
                            "Proof of Address",
                            "Utility Bill"
                        ]
                    },
                    {
                        "name": "For Company Registration",
                        "description": [
                            "Digital Signature Certificate",
                            "Director Identification Number",
                            "Memorandum of Association",
                            "Articles of Association"
                        ]
                    }
                ]
            },
            "stepsToRegister": {
                "para": "The process of registering a Private Limited Company in Karnataka involves a series of steps to ensure compliance with legal and regulatory requirements. Here’s a step-by-step guide:",
                "para1": "<h2>Step 1: Obtain DSC</h2> To initiate the company registration process, you must first obtain a <a href='https://www.registerkaro.in/digital-signature-certificate' style='text-decoration:none;'>Digital Signature Certificate (DSC)</a>. A DSC (Usually Class 3 DSC) is mandatory for all subscribers and witnesses signing the Memorandum of Association (MOA) and Articles of Association (AOA).",
                "para2": "<h2>Step 2: Apply For DIN</h2> A Director Identification Number (DIN) is essential for anyone intending to serve as a company director. One DIN suffices to act as a director in multiple companies. DIN is applied through the SPICe+ (INC-32) form during the registration process.",
                "para3": "<h2>Step 3: Unique Company Name</h2> A company’s name plays a crucial role in catching attention and making the firm stand out amidst hundreds of competitors. Select a unique name and check its availability on the Company Name Search tool.",
                "para4": "<h2>Step 4: MoA & AoA</h2> The Memorandum of Association (MOA) and Articles of Association (AOA) outline the company’s objectives, internal rules, and regulations. These documents must be prepared electronically (e-MoA and e-AoA) and filed as linked forms with SPICe+. Both MOA and AOA must be digitally signed by all subscribers before submission.",
                "para5": "<h2>Step 5: SPICe+ Form</h2> Complete the SPICe+ (INC-32) form and submit it, along with the Memorandum of Association (MoA) and Articles of Association (AoA), through the MCA portal. Ensure that you attach the necessary documents, including Digital Signature Certificate (DSC), Director Identification Number (DIN), and proof of address and identity for each director.",
                "para6": "<h2>Step 6: PAN & TAN</h2> Once incorporated, apply for a Permanent Account Number (PAN) and a Tax Deduction and Collection Account Number (TAN) for tax compliance. Then, register for <a href='https://www.registerkaro.in/gst-registration' style='text-decoration:none;'>GST registration</a> if the company's turnover exceeds ₹20 lakh (₹40 lakh for certain businesses).",
                "para7": "<h2>Step 7: Compliance Filings</h2> After incorporation comes the task of getting your business legally compliant. Submit annual financial statements (AOC-4), annual returns (MGT-7), and statutory compliance reports to the ROC each year. Failure to comply can lead to penalties and legal action.",
                "para8": "<h2>Step 8: Legal Operations</h2> Now that you are set, your company (now registered as a private limited) is all set to grow. Fill your basic details on the form to get instant assistance to register your company now!   ",
                "steps": [
                    "Obtain Digital Signature Certificates (DSC)",
                    "Apply for Director Identification Number",
                    " Reserve a Unique Company Name",
                    "Draft MoA and AoA",
                    "SPICe+ Form",
                    "Apply for PAN and TAN",
                    "Compliance Filings",
                    "Successful SetUp"
                ]
            },
            "cost_penalties": {
                "para": "Operating a business without completing the required registration can expose entrepreneurs to significant financial and legal risks. Key points include: Monetary Fines and Financial Implications (starting from ₹1,00,000-₹5,00,000), Legal and Criminal Penalties (fine & imprisonment for up to 6 months or both), Loss of Business Credibility and Operational Restrictions, Compliance and Rectification Costs, and more.",
                "para1": "As per the guidelines set by the Ministry of Corporate Affairs (MCA) and supported by various legal sources, unregistered companies may incur fines that can range from several thousand rupees to significantly higher amounts, depending on the duration and nature of non-compliance. In certain cases, fines are levied on a per day basis for continued non-compliance.",
                "para2": "Beyond monetary fines, running a business without proper registration may attract legal actions. Section 2(68) of the Companies Act defines Private Limited Company as one that is duly registered with MCA and adheres to compliance rules. Non-registration prevents a company from getting recognized as a legal entity, and it cannot conduct business dealings effectively. ",
                "para3": "In addition to the registration expenses, it’s important to be aware of potential penalties associated with non-compliance. Delays, inaccuracies in documentation, or failure to adhere to statutory requirements may result in fines or legal repercussions."
            },
            "whyChooseRegisterKaro": {
                "para1": "At RegisterKaro, we simplify the entire process of company registration with our expert services.",
                "features": [
                    "Trusted by 50,000+ Clients",
                    "Proven track record of 10,000+ successful registrations per month.",
                    "Fast document preparation and filing process.",
                    "Assistance at every step from consultation to compliance.",
                    "Transparent and budget-friendly pricing."
                ],
                "image": ""
            },
            "companyRegistrationAuthorization": {
                "para1": "Obtaining company registration authorization in Maharashtra is a critical step in ensuring your business complies with all legal and regulatory standards. This authorization confirms that your private limited company has been vetted and approved by the appropriate state and national authorities, providing you with a clear, legally recognized status. With this formal validation, businesses gain enhanced credibility and the assurance that their operations adhere to the highest standards of compliance.",
                "para2": "Take decisive action by partnering with experienced professionals who specialize in corporate compliance. Our expert team streamlines the documentation and filing process, ensuring that every regulatory requirement is met with precision."
            },
            "challenges_solutions": {
                "para": "Registering a company in Maharashtra presents its own set of challenges. Complex documentation, evolving statutory mandates, and occasional delays in the approval process can create significant hurdles for new businesses. Errors in filings or misinterpretations of legal requirements can lead to setbacks that affect both timelines and budgets.",
                "para1": "To navigate these issues, seek expert guidance for thorough documentation reviews and proactive communication with regulatory authorities. By adopting a solution-oriented approach, you can expedite the process and ensure compliance, turning challenges into opportunities for a smooth registration experience."
            }
        }
    }
}    
